snek_scripts/__init__.py
snek_scripts/cryptography.py
snek_scripts/encoder.py
snek_scripts/fracarith.py
snek_scripts/misc.py
snek_scripts/strlist.py
snek_scripts-0.1.3.dist-info/LICENSE
snek_scripts-0.1.3.dist-info/METADATA
snek_scripts-0.1.3.dist-info/WHEEL
snek_scripts-0.1.3.dist-info/top_level.txt
snek_scripts-0.1.3.dist-info/RECORD
