Metadata-Version: 2.1
Name: snek-scripts
Version: 0.1.3
Summary: A set of useful Python functions
Home-page: https://github.com/supremestdoggo/Snek-Scripts
Author: supremestdoggo
Author-email: 
License: UNKNOWN
Project-URL: Bug Tracker, https://github.com/supremestdoggo/Snek-Scripts/issues
Platform: UNKNOWN
Classifier: Programming Language :: Python :: 3
Classifier: License :: OSI Approved :: MIT License
Classifier: Operating System :: OS Independent
Requires-Python: >=3.8.2
